{
  "File Paths": [
    "/media/mass_storage/josh/Documents/S4GratingOptimizer/S4/AF2_Film.json",
    "/media/mass_storage/josh/Documents/S4GratingOptimizer/S4/AF2_Grating.json",
    "/media/mass_storage/josh/Documents/S4GratingOptimizer/S4/AF2_Peak.json",
    "/media/mass_storage/josh/Documents/S4GratingOptimizer/S4/AF2_Period.json"
  ],
  "Gratings": [
    "P350",
    "P400",
    "P475",
    "P550"
  ],
  "P350": {
    "P350_TE Optimizer Results": [
      1.9711101293789204,
      0.020420393316513893,
      0.4,
      334.57408110410813,
      72.14359823261266,
      234.60585392910565
    ],
    "P350_TE Optimizer Errors": [
      2.0458827756445415e-05,
      2.0458827756445415e-05,
      2.0458827756445415e-05,
      2.0458827756445415e-05,
      2.0458827756445415e-05,
      2.0458827756445415e-05
    ],
    "P350_TE Iterations": 43,
    "P350_TE FoM Tolerance": 1e-07,
    "P350_TE Fano Fit Parameters": [
      "Peak",
      "Gamma",
      "q",
      "Amplitude",
      "Damping"
    ],
    "P350_TE Fano Fit": [
      584.7307465246946,
      17.083614501618246,
      -0.4409967016290334,
      0.026916770577945195,
      17.135971638453995
    ],
    "P350_TE Fano Errors": [
      0.33682456253069254,
      0.7567400689976188,
      0.2495726977061773,
      0.004367578954863838,
      2.7502263542850574
    ],
    "P350_TE S4 Fano Fit Parameters": [
      "Peak",
      "Gamma",
      "q",
      "Amplitude",
      "Damping"
    ],
    "P350_TE S4 Fano Fit": [
      584.8080468207969,
      16.547513668267527,
      0.6630081338951251,
      0.07021081658720044,
      2.9168465102233214
    ],
    "P350_TE S4 Fano Errors": [
      0.3010331920180842,
      0.6675333663105469,
      0.035621648474681945,
      0.001480281530974291,
      0.10452794619134105
    ],
    "P350_TE Figure Of Merit": 204.5882775636843,
    "P350_TE Fano Error": 203.6975999028584,
    "P350_TE Overlap Error": 0.8906776608259019,
    "P350_TE Differences": [
      0.00597533577750232,
      0.28740410351933576,
      1.2188266768607243,
      0.0018743744198515095,
      202.183519412281
    ],
    "P350_TE Variables": {
      "S4 Strings": [
        "material_n",
        "material_k",
        "fill_factor",
        "period",
        "grating_thickness",
        "film_thickness"
      ],
      "S4 Guesses": [
        2.19,
        0.00022,
        0.4,
        334.57408110410813,
        72.14359823261266,
        234.60585393910566
      ]
    },
    "P350_TE Constants": {
      "Reflection": "True",
      "S4 Strings": [
        "harmonics",
        "cover_n",
        "cover_k",
        "substrate_n",
        "substrate_k"
      ],
      "S4 Values": [
        21,
        1,
        0,
        1.4542,
        0
      ]
    },
    "P350_TE Wavelength Range": [
      530,
      661,
      1
    ],
    "P350_TM Optimizer Results": [
      2.0973617546856596,
      79.76954070304133,
      262.8934333097087
    ],
    "P350_TM Optimizer Errors": [
      4.0519388080089073e-10,
      1.3696489637252184e-06,
      2.004546984569032e-06
    ],
    "P350_TM Iterations": 44,
    "P350_TM FoM Tolerance": 1e-07,
    "P350_TM Fano Fit Parameters": [
      "Peak",
      "Gamma",
      "q",
      "Amplitude",
      "Damping"
    ],
    "P350_TM Fano Fit": [
      589.2327606808896,
      8.68880958155116,
      0.8913230864624886,
      0.038023546116001346,
      5.706354665827224
    ],
    "P350_TM Fano Errors": [
      0.1450995587175802,
      0.3153851485233726,
      0.0773412711897429,
      0.0011589219437527975,
      0.22455074280510726
    ],
    "P350_TM S4 Fano Fit Parameters": [
      "Peak",
      "Gamma",
      "q",
      "Amplitude",
      "Damping"
    ],
    "P350_TM S4 Fano Fit": [
      589.0639809400803,
      15.08930097488948,
      -0.21498086694210103,
      0.09439403634263886,
      2.4450424783292224
    ],
    "P350_TM S4 Fano Errors": [
      0.1776347107179436,
      0.3604718838520163,
      0.013811409907559032,
      0.0006850088354238625,
      0.030301778975697354
    ],
    "P350_TM Figure Of Merit": 53.30948811106128,
    "P350_TM Fano Error": 52.85801993091557,
    "P350_TM Overlap Error": 0.4514681801457066,
    "P350_TM Differences": [
      0.02848660090762538,
      40.96629007619792,
      1.2239084373186242,
      0.003177632168391436,
      10.636157184322999
    ],
    "P350_TM Variables": {
      "S4 Strings": [
        "material_n",
        "grating_thickness",
        "film_thickness"
      ],
      "S4 Guesses": [
        2.0973617546856596,
        79.76954070304133,
        262.8934333197087
      ]
    },
    "P350_TM Constants": {
      "Reflection": "True",
      "S4 Strings": [
        "harmonics",
        "cover_n",
        "cover_k",
        "substrate_n",
        "substrate_k",
        "material_k",
        "fill_factor",
        "period"
      ],
      "S4 Values": [
        21,
        1,
        0,
        1.4542,
        0,
        0.02042039338850535,
        0.4,
        334.5740812752404
      ]
    },
    "P350_TM Wavelength Range": [
      546,
      671,
      1
    ]
  },
  "P400": {
    "P400_TE Optimizer Results": [
      1.7792358650862976,
      0.07048823922468596,
      0.7264452783395587,
      395.94907478765674,
      124.97066656059023,
      234.88234624488433
    ],
    "P400_TE Optimizer Errors": [
      4.783034055979937e-06,
      4.783034055979937e-06,
      4.783034055979937e-06,
      4.783034055979937e-06,
      4.783034055979937e-06,
      4.783034055979937e-06
    ],
    "P400_TE Iterations": 50,
    "P400_TE FoM Tolerance": 1e-07,
    "P400_TE Fano Fit Parameters": [
      "Peak",
      "Gamma",
      "q",
      "Amplitude",
      "Damping"
    ],
    "P400_TE Fano Fit": [
      643.4264496409368,
      26.062806968892353,
      -1.4567709500511083,
      0.06540300152085504,
      4.230973112747704
    ],
    "P400_TE Fano Errors": [
      0.8945046586511346,
      2.001416031093321,
      0.19282215922233362,
      0.008730363409913601,
      0.7330426809745979
    ],
    "P400_TE S4 Fano Fit Parameters": [
      "Peak",
      "Gamma",
      "q",
      "Amplitude",
      "Damping"
    ],
    "P400_TE S4 Fano Fit": [
      639.3359157525373,
      30.352712351802182,
      0.04104422228251664,
      0.04952700281970078,
      1.5642842534352335
    ],
    "P400_TE S4 Fano Errors": [
      3.6435914200000505,
      8.848087296851695,
      0.05578025981028478,
      0.0022891982363611283,
      0.09589345142998562
    ],
    "P400_TE Figure Of Merit": 47.83047878933426,
    "P400_TE Fano Error": 44.49068749665209,
    "P400_TE Overlap Error": 3.3397912926821647,
    "P400_TE Differences": [
      16.732467492144547,
      18.40328819431873,
      2.243450290472807,
      0.0002520473347590518,
      7.111229472381246
    ],
    "P400_TE Variables": {
      "S4 Strings": [
        "material_n",
        "material_k",
        "fill_factor",
        "period",
        "grating_thickness",
        "film_thickness"
      ],
      "S4 Guesses": [
        2.18,
        0.00071,
        0.7264452783395587,
        395.94907478765674,
        124.97066656059023,
        234.88234625488434
      ]
    },
    "P400_TE Constants": {
      "Reflection": "True",
      "S4 Strings": [
        "harmonics",
        "cover_n",
        "cover_k",
        "substrate_n",
        "substrate_k"
      ],
      "S4 Values": [
        21,
        1,
        0,
        1.4542,
        0
      ]
    },
    "P400_TE Wavelength Range": [
      569,
      716,
      1
    ],
    "P400_TM Optimizer Results": [
      2.0007460935410557,
      128.3004343621669,
      246.36425560057253
    ],
    "P400_TM Optimizer Errors": [
      3.551246020824272e-05,
      3.551246020824272e-05,
      3.551246020824272e-05
    ],
    "P400_TM Iterations": 47,
    "P400_TM FoM Tolerance": 1e-07,
    "P400_TM Fano Fit Parameters": [
      "Peak",
      "Gamma",
      "q",
      "Amplitude",
      "Damping"
    ],
    "P400_TM Fano Fit": [
      655.8693937330606,
      12.543961879182262,
      -0.8331954468968118,
      0.03635577314733834,
      3.9797532364178725
    ],
    "P400_TM Fano Errors": [
      0.386345217762321,
      0.843187950990776,
      0.09167323612941469,
      0.0017413160877489996,
      0.2953112251731946
    ],
    "P400_TM S4 Fano Fit Parameters": [
      "Peak",
      "Gamma",
      "q",
      "Amplitude",
      "Damping"
    ],
    "P400_TM S4 Fano Fit": [
      644.6843662812048,
      27.095933231618925,
      0.6212566758692968,
      0.06721796779037238,
      0.006442537470226976
    ],
    "P400_TM S4 Fano Errors": [
      0.5992166472464587,
      1.0248939020643928,
      0.025186903354728715,
      0.0011443009887317798,
      0.03773922038472348
    ],
    "P400_TM Figure Of Merit": 355.12456501356826,
    "P400_TM Fano Error": 354.7682907037547,
    "P400_TM Overlap Error": 0.35627430981356195,
    "P400_TM Differences": [
      125.10483909876854,
      211.7598702421373,
      2.1154309774188396,
      0.0009524750581845193,
      15.787197910371829
    ],
    "P400_TM Variables": {
      "S4 Strings": [
        "material_n",
        "grating_thickness",
        "film_thickness"
      ],
      "S4 Guesses": [
        2.0007460933351973,
        128.3004343510408,
        246.36425558823728
      ]
    },
    "P400_TM Constants": {
      "Reflection": "True",
      "S4 Strings": [
        "harmonics",
        "cover_n",
        "cover_k",
        "substrate_n",
        "substrate_k",
        "material_k",
        "fill_factor",
        "period"
      ],
      "S4 Values": [
        21,
        1,
        0,
        1.4542,
        0,
        0.07048823922468596,
        0.7264452783395587,
        395.94907478765674
      ]
    },
    "P400_TM Wavelength Range": [
      584,
      717,
      1
    ]
  },
  "P475": {
    "P475_TE Optimizer Results": [
      1.856508171401404,
      0.38980985258247763,
      0.6897749859185927,
      450.3642507416951,
      53.459074959173655,
      249.10175287105724
    ],
    "P475_TE Optimizer Errors": [
      1.214628045056321e-07,
      1.214628045056321e-07,
      1.214628045056321e-07,
      1.214628045056321e-07,
      1.214628045056321e-07,
      1.214628045056321e-07
    ],
    "P475_TE Iterations": 13,
    "P475_TE FoM Tolerance": 1e-07,
    "P475_TE Fano Fit Parameters": [
      "Peak",
      "Amplitude",
      "Assymetry",
      "Gamma",
      "Offset"
    ],
    "P475_TE Fano Fit": [
      732.9768691647951,
      176.75840762022366,
      -0.1014664785367351,
      -0.00015193833578176327,
      -176.66332466607193
    ],
    "P475_TE Fano Errors": [
      74.83155880317341,
      558495.4302545901,
      4739.722463076552,
      7.092970451165935,
      558495.430293716
    ],
    "P475_TE S4 Fano Fit Parameters": [
      "Peak",
      "Amplitude",
      "Assymetry",
      "Gamma",
      "Offset"
    ],
    "P475_TE S4 Fano Fit": [
      732.9864670728116,
      176.7564111716796,
      -0.011000598621872557,
      3.719772445301728e-07,
      -176.66531988757916
    ],
    "P475_TE S4 Fano Errors": [
      24.454016730062854,
      NaN,
      7.658455829384408,
      0.0006149429676490983,
      NaN
    ],
    "P475_TE Figure Of Merit": 1.2151672282797676,
    "P475_TE Fano Error": 0.008284185181147626,
    "P475_TE Overlap Error": 1.20688304309862,
    "P475_TE Differences": [
      9.211983829378446e-05,
      3.985806789145802e-06,
      0.00818407542877033,
      2.3198431454167498e-08,
      3.980908862910825e-06
    ],
    "P475_TE Variables": {
      "S4 Strings": [
        "material_n",
        "material_k",
        "fill_factor",
        "period",
        "grating_thickness",
        "film_thickness"
      ],
      "S4 Guesses": [
        2.16,
        0.00087,
        0.6897749853611111,
        450.36425050584916,
        53.45907491442792,
        249.10175285316942
      ]
    },
    "P475_TE Constants": {
      "Reflection": "True",
      "S4 Strings": [
        "harmonics",
        "cover_n",
        "cover_k",
        "substrate_n",
        "substrate_k"
      ],
      "S4 Values": [
        21,
        1,
        0,
        1.4542,
        0
      ]
    },
    "P475_TE Wavelength Range": [
      661,
      801,
      1
    ],
    "P475_TM Optimizer Results": [
      1.8368588530540448,
      67.97083632872733,
      224.87341650485254
    ],
    "P475_TM Optimizer Errors": [
      0.00012221874659946864,
      0.00012221874659946864,
      0.00012221874659946864
    ],
    "P475_TM Iterations": 12,
    "P475_TM FoM Tolerance": 1e-07,
    "P475_TM Fano Fit Parameters": [
      "Peak",
      "Gamma",
      "q",
      "Amplitude",
      "Damping"
    ],
    "P475_TM Fano Fit": [
      746.808351682772,
      6.810918029131304,
      -0.1103371161092892,
      0.007975295703344439,
      17.836295838728425
    ],
    "P475_TM Fano Errors": [
      0.16129580016349637,
      0.34483994291633185,
      0.29576009865016906,
      0.0008992511097908291,
      1.9937867088549337
    ],
    "P475_TM S4 Fano Fit Parameters": [
      "Peak",
      "Gamma",
      "q",
      "Amplitude",
      "Damping"
    ],
    "P475_TM S4 Fano Fit": [
      743.3883469870293,
      37.25686004931906,
      -0.006328256964543763,
      0.04333143404915446,
      1.0020201338244992
    ],
    "P475_TM S4 Fano Errors": [
      2.5260799297347547,
      3.709507470690278,
      0.00034990772838060095,
      3.0706839927211936e-05,
      0.002007710853732116
    ],
    "P475_TM Figure Of Merit": 1222.1806460871114,
    "P475_TM Fano Error": 1222.0567240235546,
    "P475_TM Overlap Error": 0.12392206355681132,
    "P475_TM Differences": [
      11.696432118902152,
      926.9553854966343,
      0.010817842780591495,
      0.0012500565187280577,
      283.3928385087186
    ],
    "P475_TM Variables": {
      "S4 Strings": [
        "material_n",
        "grating_thickness",
        "film_thickness"
      ],
      "S4 Guesses": [
        1.8368588530540446,
        67.97083632872732,
        224.87341651485252
      ]
    },
    "P475_TM Constants": {
      "Reflection": "True",
      "S4 Strings": [
        "harmonics",
        "cover_n",
        "cover_k",
        "substrate_n",
        "substrate_k",
        "material_k",
        "fill_factor",
        "period"
      ],
      "S4 Values": [
        21,
        1,
        0,
        1.4542,
        0,
        0.38980985258247763,
        0.6897749859185927,
        450.3642507416951
      ]
    },
    "P475_TM Wavelength Range": [
      691,
      806,
      1
    ]
  },
  "P550": {
    "P550_TE Optimizer Results": [
      2.073963696758029,
      0.03579966143973167,
      0.7709152587883532,
      545.3995193434946,
      247.21651457923156,
      238.21285397288446
    ],
    "P550_TE Optimizer Errors": [
      1.2930377913414995e-06,
      1.2930377913414995e-06,
      1.2930377913414995e-06,
      1.2930377913414995e-06,
      1.2930377913414995e-06,
      1.2930377913414995e-06
    ],
    "P550_TE Iterations": 48,
    "P550_TE FoM Tolerance": 1e-07,
    "P550_TE Fano Fit Parameters": [
      "Peak",
      "Gamma",
      "q",
      "Amplitude",
      "Damping"
    ],
    "P550_TE Fano Fit": [
      822.0378531280438,
      34.708530292045964,
      1.333324236890515,
      0.08219480105302941,
      0.1267160106570279
    ],
    "P550_TE Fano Errors": [
      0.6376759656756941,
      1.1903281120187441,
      0.053313932120834226,
      0.003626785817669415,
      0.0858446245943877
    ],
    "P550_TE S4 Fano Fit Parameters": [
      "Peak",
      "Gamma",
      "q",
      "Amplitude",
      "Damping"
    ],
    "P550_TE S4 Fano Fit": [
      822.0513792153628,
      34.78223369734504,
      -1.6876535335539566,
      0.07327117438229118,
      0.0065264052409037005
    ],
    "P550_TE S4 Fano Errors": [
      0.20617631494785402,
      0.3287625254191137,
      0.02033855354071856,
      0.001140088611571346,
      0.04387204635500361
    ],
    "P550_TE Figure Of Merit": 12.930376716517102,
    "P550_TE Fano Error": 9.146447008873531,
    "P550_TE Overlap Error": 3.783929707643571,
    "P550_TE Differences": [
      0.00018295503815988397,
      0.005432191952680149,
      9.12630668951965,
      7.963111295871071e-05,
      0.01444554125008363
    ],
    "P550_TE Variables": {
      "S4 Strings": [
        "material_n",
        "material_k",
        "fill_factor",
        "period",
        "grating_thickness",
        "film_thickness"
      ],
      "S4 Guesses": [
        2.16,
        0.0019,
        0.7709152587883532,
        545.3995193434946,
        247.21651457923156,
        238.21285398288447
      ]
    },
    "P550_TE Constants": {
      "Reflection": "True",
      "S4 Strings": [
        "harmonics",
        "cover_n",
        "cover_k",
        "substrate_n",
        "substrate_k"
      ],
      "S4 Values": [
        21,
        1,
        0,
        1.4542,
        0
      ]
    },
    "P550_TE Wavelength Range": [
      766,
      899,
      1
    ],
    "P550_TM Optimizer Results": [
      2.03622529679262,
      214.73838237183085,
      228.89297401796503
    ],
    "P550_TM Optimizer Errors": [
      6.709980086308252e-07,
      6.709980086308252e-07,
      6.709980086308252e-07
    ],
    "P550_TM Iterations": 38,
    "P550_TM FoM Tolerance": 1e-07,
    "P550_TM Fano Fit Parameters": [
      "Peak",
      "Gamma",
      "q",
      "Amplitude",
      "Damping"
    ],
    "P550_TM Fano Fit": [
      834.7069138695254,
      22.11683996391003,
      1.0678638798017421,
      0.03246442349157659,
      1.2681965999411609
    ],
    "P550_TM Fano Errors": [
      1.449837727115568,
      2.3543271176899894,
      0.1002522777233899,
      0.00428658699997622,
      0.41843253693596744
    ],
    "P550_TM S4 Fano Fit Parameters": [
      "Peak",
      "Gamma",
      "q",
      "Amplitude",
      "Damping"
    ],
    "P550_TM S4 Fano Fit": [
      834.3372362515323,
      23.453944460371417,
      2.716763933814613,
      0.024775605774775247,
      2.4964859490407862
    ],
    "P550_TM S4 Fano Errors": [
      0.14385133968150274,
      0.30098401253684887,
      0.10720986709381904,
      0.0011730322130896504,
      0.26028675495370623
    ],
    "P550_TM Figure Of Merit": 6.7099799163374145,
    "P550_TM Fano Error": 6.152135206855371,
    "P550_TM Overlap Error": 0.5578447094820431,
    "P550_TM Differences": [
      0.1366615412450035,
      1.7878484344572563,
      2.7188713881236484,
      5.9117917882198244e-05,
      1.5086947251115814
    ],
    "P550_TM Variables": {
      "S4 Strings": [
        "material_n",
        "grating_thickness",
        "film_thickness"
      ],
      "S4 Guesses": [
        2.036225296792623,
        214.73838237183082,
        228.892974027965
      ]
    },
    "P550_TM Constants": {
      "Reflection": "True",
      "S4 Strings": [
        "harmonics",
        "cover_n",
        "cover_k",
        "substrate_n",
        "substrate_k",
        "material_k",
        "fill_factor",
        "period"
      ],
      "S4 Values": [
        21,
        1,
        0,
        1.4542,
        0,
        0.03579962477810114,
        0.7709152643067188,
        545.3995198231395
      ]
    },
    "P550_TM Wavelength Range": [
      784,
      877,
      1
    ]
  }
}
